polyclash/__init__.py
polyclash/client.py
polyclash/server.py
polyclash/data/__init__.py
polyclash/data/data.py
polyclash/game/__init__.py
polyclash/game/board.py
polyclash/game/controller.py
polyclash/game/player.py
polyclash/game/timer.py
polyclash/gui/__init__.py
polyclash/gui/constants.py
polyclash/gui/dialogs.py
polyclash/gui/icons.py
polyclash/gui/main.py
polyclash/gui/mesh.py
polyclash/gui/overly_info.py
polyclash/gui/overly_map.py
polyclash/gui/view_sphere.py
polyclash/util/__init__.py
polyclash/util/api.py
polyclash/util/logging.py
polyclash/util/storage.py
polyclash/workers/__init__.py
polyclash/workers/ai_play.py
polyclash/workers/network.py
polyclash-0.0.6.dist-info/licenses/LICENSE
polyclash-0.0.6.dist-info/METADATA
polyclash-0.0.6.dist-info/WHEEL
polyclash-0.0.6.dist-info/entry_points.txt
polyclash-0.0.6.dist-info/top_level.txt
polyclash-0.0.6.dist-info/RECORD
