Metadata-Version: 2.4
Name: polyclash
Version: 0.0.6
Summary: A python 3d spherical Go game on a snub dodecahedron board
Home-page: https://github.com/spherical-go/polyclash
Author: Mingli Yuan
Author-email: Mingli Yuan <mingli.yuan@gmail.com>
License: MIT License
Project-URL: Homepage, https://github.com/spherical-go/polyclash
Project-URL: Documentation, https://github.com/spherical-go/polyclash
Project-URL: Source, https://github.com/spherical-go/polyclash
Project-URL: Tracker, https://github.com/spherical-go/polyclash/issues
Classifier: Programming Language :: Python :: 3
Classifier: License :: OSI Approved :: MIT License
Classifier: Operating System :: OS Independent
Requires-Python: >=3.10
License-File: LICENSE
Requires-Dist: numpy==2.3.3
Requires-Dist: scipy==1.16.2
Requires-Dist: PyQt5==5.15.11
Requires-Dist: pyvista==0.46.3
Requires-Dist: pyvistaqt==0.11.3
Requires-Dist: requests==2.32.5
Requires-Dist: python-socketio[client]==5.13.0
Requires-Dist: flask==3.1.2
Requires-Dist: flask-socketio==5.5.1
Requires-Dist: loguru==0.7.3
Requires-Dist: redis==6.4.0
Provides-Extra: dev
Requires-Dist: pytest; extra == "dev"
Requires-Dist: pytest-cov; extra == "dev"
Requires-Dist: pytest-mock; extra == "dev"
Requires-Dist: pytest-benchmark; extra == "dev"
Requires-Dist: pytest-asyncio; extra == "dev"
Requires-Dist: pytest-qt; extra == "dev"
Requires-Dist: pytest-flask; extra == "dev"
Dynamic: author
Dynamic: home-page
Dynamic: license-file
Dynamic: requires-python
